tensorboard_logger/__init__.py
tensorboard_logger/crc32c.py
tensorboard_logger/tensorboard_logger.py
tensorboard_logger/tf_protobuf/__init__.py
tensorboard_logger/tf_protobuf/event_pb2.py
tensorboard_logger/tf_protobuf/summary_pb2.py
tensorboard_logger-0.0.4.dist-info/DESCRIPTION.rst
tensorboard_logger-0.0.4.dist-info/METADATA
tensorboard_logger-0.0.4.dist-info/RECORD
tensorboard_logger-0.0.4.dist-info/WHEEL
tensorboard_logger-0.0.4.dist-info/metadata.json
tensorboard_logger-0.0.4.dist-info/top_level.txt
