Metadata-Version: 2.0
Name: tensorboard-logger
Version: 0.0.4
Summary: Log TensorBoard events without Tensorflow
Home-page: https://github.com/TeamHG-Memex/tensorboard_logger
Author: Konstantin Lopuhin
Author-email: kostia.lopuhin@gmail.com
License: MIT license
Platform: UNKNOWN
Classifier: Development Status :: 2 - Pre-Alpha
Classifier: Intended Audience :: Developers
Classifier: License :: OSI Approved :: MIT License
Classifier: Natural Language :: English
Classifier: Programming Language :: Python :: 2
Classifier: Programming Language :: Python :: 2.7
Classifier: Programming Language :: Python :: 3
Classifier: Programming Language :: Python :: 3.4
Classifier: Programming Language :: Python :: 3.5
Requires-Dist: protobuf
Requires-Dist: six
